mfd_ethtool/__init__.py
mfd_ethtool/base.py
mfd_ethtool/const.py
mfd_ethtool/exceptions.py
mfd_ethtool/parser.py
mfd_ethtool/structures.py
mfd_ethtool-3.14.0.dist-info/licenses/AUTHORS.md
mfd_ethtool-3.14.0.dist-info/licenses/LICENSE.md
mfd_ethtool-3.14.0.dist-info/METADATA
mfd_ethtool-3.14.0.dist-info/WHEEL
mfd_ethtool-3.14.0.dist-info/top_level.txt
mfd_ethtool-3.14.0.dist-info/RECORD
