Metadata-Version: 2.4
Name: mfd-ethtool
Version: 3.14.0
Summary: Module wrapping multiple ethtool operations.
Project-URL: Homepage, https://github.com/intel/mfd
Project-URL: Repository, https://github.com/intel/mfd-ethtool
Project-URL: Issues, https://github.com/intel/mfd-ethtool/issues
Project-URL: Changelog, https://github.com/intel/mfd-ethtool/blob/main/CHANGELOG.md
Requires-Python: <3.14,>=3.10
License-File: LICENSE.md
License-File: AUTHORS.md
Requires-Dist: mfd-base-tool>=2.7.0
Requires-Dist: mfd-common-libs>=1.11.0
Requires-Dist: mfd-typing>=1.23.0
Requires-Dist: mfd-kernel-namespace>=1.8.0
Dynamic: license-file
